{
  "skin_temperature": {
    "class": 400012,
    "status": "ack_no_data",
    "ack_code": 207,
    "ack_cmd": 3,
    "ack_sequence": 4
  },
  "emotion": {
    "class": 500031,
    "status": "error_tlv",
    "error_tlvs": {
      "0x7f": "000186a4"
    }
  },
  "sleep_apnea": {
    "class": 500002,
    "status": "error_tlv",
    "error_tlvs": {
      "0x7f": "000186a4"
    }
  },
  "arterial_stiffness": {
    "class": 400017,
    "status": "error_tlv",
    "error_tlvs": {
      "0x7f": "000186a4"
    }
  },
  "altitude": {
    "class": 200003,
    "status": "error_tlv",
    "error_tlvs": {
      "0x7f": "000186a4"
    }
  },
  "blood_pressure": {
    "class": 10002,
    "status": "error_tlv",
    "error_tlvs": {
      "0x7f": "000186a4"
    }
  },
  "lake_louise_ams": {
    "class": 500006,
    "status": "error_tlv",
    "error_tlvs": {
      "0x7f": "000186a4"
    }
  },
  "hrv": {
    "class": 500044,
    "status": "error_tlv",
    "error_tlvs": {
      "0x7f": "000186a4"
    }
  }
}
